{"Update_3": [], "Update_4": ["IFEC"], "Update_5": ["BA", "UNIQ", "WHA", "CKP", "RS", "MONO", "CBG", "LHBANK", "BEAUTY", "ASP", "U", "SEPPE", "S"], "Update_6": ["SCN", "GL", "PTG", "BLA", "PLANB", "PLAT", "SAMTEL", "GPSC", "SCCC", "VNG", "TASCO", "TU", "CHG", "WORK", "EPG"], "Update_7": ["BDMS", "SGP", "BEM"], "Update_8": ["TRC", "MTLS", "ERW", "IFEC", "GLOBAL", "JWD", "COM7", "BCH", "TVO"], "Update_9": ["PSH"], "Update_10": ["SCN", "SUPER", "KAMART", "VIBHA", "SPRC", "THANI", "BIG", "TKN"], "Update_11": ["BJC", "RATCH", "BPP", "MONO", "ANAN", "GFPT", "MEGA", "SCCC", "MALEE", "BCPG", "WORK", "EA", "PTL"], "Update_12": ["SGP", "GGC", "TPIPP", "JMART", "STA", "UV", "ORI", "ESSO", "PSL", "WHAUP", "MC", "JWD", "HANA"], "Update_13": ["RATCH", "BLA", "TOA", "RS", "DELTA", "PRM", "BGRIM", "ERW", "THANI", "GLOW", "TTW"], "Update_14": ["PLANB", "ANAN", "GULF", "AEONTS", "GOLD", "MBK"], "Update_15": ["BEC"], "Update_16": ["OSP", "JMT", "JAS"], "Update_17": ["AWC"]}